README
setup.py
bambu_comments/__init__.py
bambu_comments/admin.py
bambu_comments/apps.py
bambu_comments/context_processors.py
bambu_comments/forms.py
bambu_comments/helpers.py
bambu_comments/models.py
bambu_comments/notifications.py
bambu_comments/querysets.py
bambu_comments/search_indexes.py
bambu_comments.egg-info/PKG-INFO
bambu_comments.egg-info/SOURCES.txt
bambu_comments.egg-info/dependency_links.txt
bambu_comments.egg-info/requires.txt
bambu_comments.egg-info/top_level.txt
bambu_comments/migrations/0001_initial.py
bambu_comments/migrations/__init__.py
bambu_comments/templates/comments/comment.inc.html
bambu_comments/templates/comments/form.inc.html
bambu_comments/templates/comments/list.inc.html
bambu_comments/templates/comments/mail.txt
bambu_comments/templates/search/indexes/bambu_comments/comment_text.txt
bambu_comments/templatetags/__init__.py
bambu_comments/templatetags/comments.py