Metadata-Version: 1.1
Name: bambu-comments
Version: 3.2
Summary: Generic model commenting
Home-page: https://github.com/iamsteadman/bambu-comments
Author: Steadman
Author-email: mark@steadman.io
License: UNKNOWN
Platform: UNKNOWN
Classifier: Development Status :: 4 - Beta
Classifier: Environment :: Web Environment
Classifier: Framework :: Django
